{
    "FaceDetails": [
        {
            "AgeRange": {
                "High": 25,
                "Low": 13
            },
            "Beard": {
                "Confidence": 89.48806762695312,
                "Value": false
            },
            "BoundingBox": {
                "Height": 0.5145281553268433,
                "Left": 0.23387011885643005,
                "Top": 0.2829042077064514,
                "Width": 0.5269727110862732
            },
            "Confidence": 99.99878692626953,
            "Emotions": [
                {
                    "Confidence": 25.97077178955078,
                    "Type": "DISGUSTED"
                },
                {
                    "Confidence": 15.880882263183594,
                    "Type": "CALM"
                },
                {
                    "Confidence": 15.239110946655273,
                    "Type": "CONFUSED"
                },
                {
                    "Confidence": 13.347503662109375,
                    "Type": "ANGRY"
                },
                {
                    "Confidence": 11.965688705444336,
                    "Type": "HAPPY"
                },
                {
                    "Confidence": 9.679051399230957,
                    "Type": "SAD"
                },
                {
                    "Confidence": 5.244476318359375,
                    "Type": "SURPRISED"
                },
                {
                    "Confidence": 2.672515869140625,
                    "Type": "FEAR"
                }
            ],
            "Eyeglasses": {
                "Confidence": 99.86773681640625,
                "Value": false
            },
            "EyesOpen": {
                "Confidence": 92.01866149902344,
                "Value": true
            },
            "Gender": {
                "Confidence": 90.84234619140625,
                "Value": "Male"
            },
            "Landmarks": [
                {
                    "Type": "eyeLeft",
                    "X": 0.37861713767051697,
                    "Y": 0.44680267572402954
                },
                {
                    "Type": "eyeRight",
                    "X": 0.6247749924659729,
                    "Y": 0.4478144645690918
                },
                {
                    "Type": "mouthLeft",
                    "X": 0.40043631196022034,
                    "Y": 0.6492821574211121
                },
                {
                    "Type": "mouthRight",
                    "X": 0.6063975095748901,
                    "Y": 0.6502552032470703
                },
                {
                    "Type": "nose",
                    "X": 0.5045655369758606,
                    "Y": 0.5444230437278748
                },
                {
                    "Type": "leftEyeBrowLeft",
                    "X": 0.28489989042282104,
                    "Y": 0.4054037630558014
                },
                {
                    "Type": "leftEyeBrowRight",
                    "X": 0.35759276151657104,
                    "Y": 0.3755221366882324
                },
                {
                    "Type": "leftEyeBrowUp",
                    "X": 0.4294738471508026,
                    "Y": 0.3842000365257263
                },
                {
                    "Type": "rightEyeBrowLeft",
                    "X": 0.5706868767738342,
                    "Y": 0.38463079929351807
                },
                {
                    "Type": "rightEyeBrowRight",
                    "X": 0.6415882706642151,
                    "Y": 0.3763585686683655
                },
                {
                    "Type": "rightEyeBrowUp",
                    "X": 0.7121046185493469,
                    "Y": 0.40657830238342285
                },
                {
                    "Type": "leftEyeLeft",
                    "X": 0.33413586020469666,
                    "Y": 0.44749802350997925
                },
                {
                    "Type": "leftEyeRight",
                    "X": 0.4268578886985779,
                    "Y": 0.449380487203598
                },
                {
                    "Type": "leftEyeUp",
                    "X": 0.3776385486125946,
                    "Y": 0.4362807273864746
                },
                {
                    "Type": "leftEyeDown",
                    "X": 0.37939244508743286,
                    "Y": 0.4560907781124115
                },
                {
                    "Type": "rightEyeLeft",
                    "X": 0.5754668712615967,
                    "Y": 0.44994449615478516
                },
                {
                    "Type": "rightEyeRight",
                    "X": 0.6675583720207214,
                    "Y": 0.44869598746299744
                },
                {
                    "Type": "rightEyeUp",
                    "X": 0.6248083710670471,
                    "Y": 0.4372134804725647
                },
                {
                    "Type": "rightEyeDown",
                    "X": 0.6231088638305664,
                    "Y": 0.45699724555015564
                },
                {
                    "Type": "noseLeft",
                    "X": 0.45574620366096497,
                    "Y": 0.5736916065216064
                },
                {
                    "Type": "noseRight",
                    "X": 0.5469304323196411,
                    "Y": 0.5739336609840393
                },
                {
                    "Type": "mouthUp",
                    "X": 0.5020015239715576,
                    "Y": 0.6206251382827759
                },
                {
                    "Type": "mouthDown",
                    "X": 0.5017618536949158,
                    "Y": 0.683431088924408
                },
                {
                    "Type": "leftPupil",
                    "X": 0.37861713767051697,
                    "Y": 0.44680267572402954
                },
                {
                    "Type": "rightPupil",
                    "X": 0.6247749924659729,
                    "Y": 0.4478144645690918
                },
                {
                    "Type": "upperJawlineLeft",
                    "X": 0.22776195406913757,
                    "Y": 0.4691705107688904
                },
                {
                    "Type": "midJawlineLeft",
                    "X": 0.2800929844379425,
                    "Y": 0.684279203414917
                },
                {
                    "Type": "chinBottom",
                    "X": 0.5012611150741577,
                    "Y": 0.7922846078872681
                },
                {
                    "Type": "midJawlineRight",
                    "X": 0.7150982022285461,
                    "Y": 0.6850444674491882
                },
                {
                    "Type": "upperJawlineRight",
                    "X": 0.7637233734130859,
                    "Y": 0.4702880382537842
                }
            ],
            "MouthOpen": {
                "Confidence": 68.45278930664062,
                "Value": false
            },
            "Mustache": {
                "Confidence": 98.49742889404297,
                "Value": false
            },
            "Pose": {
                "Pitch": 8.733906745910645,
                "Roll": 0.19401589035987854,
                "Yaw": 1.0718944072723389
            },
            "Quality": {
                "Brightness": 75.76744842529297,
                "Sharpness": 73.32209777832031
            },
            "Smile": {
                "Confidence": 86.09686279296875,
                "Value": false
            },
            "Sunglasses": {
                "Confidence": 99.95771026611328,
                "Value": false
            }
        }
    ]
}